nustack/__init__.py
nustack/__main__.py
nustack/extensionbase.py
nustack/interpreter.py
nustack/tokenize.py
nustack/utils.py
nustack/doc/__init__.py
nustack/doc/gen.py
nustack/doc/genall.py
nustack/stdlib/Hash.py
nustack/stdlib/IO.py
nustack/stdlib/Math.py
nustack/stdlib/Path.py
nustack/stdlib/Requests.py
nustack/stdlib/Seq.py
nustack/stdlib/Shell.py
nustack/stdlib/String.py
nustack/stdlib/Time.py
nustack/stdlib/Turtle.py
nustack/stdlib/__init__.py
nustack/stdlib/builtins.py
nustack-0.11.0.dist-info/DESCRIPTION.rst
nustack-0.11.0.dist-info/METADATA
nustack-0.11.0.dist-info/RECORD
nustack-0.11.0.dist-info/WHEEL
nustack-0.11.0.dist-info/entry_points.txt
nustack-0.11.0.dist-info/metadata.json
nustack-0.11.0.dist-info/top_level.txt
