Metadata-Version: 2.0
Name: nustack
Version: 0.11.0
Summary: Nustack programming langusge
Home-page: https://github.com/BookOwl/nustack
Author: Matthew S. (BookOwl)
Author-email: Unknown
License: MIT
Keywords: nustack programming language
Platform: UNKNOWN
Classifier: Development Status :: 3 - Alpha
Classifier: Intended Audience :: Developers
Classifier: License :: OSI Approved :: MIT License
Classifier: Programming Language :: Python :: 3
Classifier: Programming Language :: Python :: 3.1
Classifier: Programming Language :: Python :: 3.2
Classifier: Programming Language :: Python :: 3.3
Classifier: Programming Language :: Python :: 3.4
Classifier: Programming Language :: Python :: 3.5
Requires-Dist: requests (>=2.8,<3)
